exomagpy/__init__.py
exomagpy/download.py
exomagpy/get_lightcurves.py
exomagpy/predictExo.py
exomagpy-1.3.0.dist-info/METADATA
exomagpy-1.3.0.dist-info/WHEEL
exomagpy-1.3.0.dist-info/top_level.txt
exomagpy-1.3.0.dist-info/RECORD
